{"data": [{"name": "北投區", "data": [41.0, 3.0, 0.0, 0.0, 0.0, 0.0, 0.0, 0.0, 0.0, 0.0, 0.0, 0.0, 0.0]}, {"name": "士林區", "data": [4.0, 63.0, 0.0, 0.0, 0.0, 0.0, 2.0, 2.0, 0.0, 0.0, 0.0, 0.0, 0.0]}, {"name": "內湖區", "data": [0.0, 0.0, 40.0, 1.0, 1.0, 1.0, 3.0, 0.0, 0.0, 0.0, 0.0, 0.0, 0.0]}, {"name": "南港區", "data": [0.0, 0.0, 1.0, 30.0, 2.0, 5.0, 0.0, 0.0, 0.0, 0.0, 0.0, 0.0, 0.0]}, {"name": "松山區", "data": [0.0, 0.0, 1.0, 2.0, 48.0, 9.0, 9.0, 1.0, 1.0, 0.0, 7.0, 0.0, 0.0]}, {"name": "信義區", "data": [0.0, 0.0, 1.0, 5.0, 9.0, 88.0, 1.0, 0.0, 1.0, 0.0, 16.0, 0.0, 0.0]}, {"name": "中山區", "data": [0.0, 2.0, 3.0, 0.0, 9.0, 1.0, 83.0, 10.0, 6.0, 1.0, 6.0, 0.0, 0.0]}, {"name": "大同區", "data": [1.0, 2.0, 0.0, 0.0, 1.0, 0.0, 10.0, 36.0, 3.0, 4.0, 1.0, 0.0, 0.0]}, {"name": "中正區", "data": [0.0, 0.0, 0.0, 0.0, 1.0, 1.0, 6.0, 4.0, 51.0, 10.0, 21.0, 2.0, 0.0]}, {"name": "萬華區", "data": [0.0, 0.0, 0.0, 0.0, 0.0, 0.0, 1.0, 3.0, 10.0, 34.0, 1.0, 0.0, 0.0]}, {"name": "大安區", "data": [0.0, 0.0, 0.0, 0.0, 7.0, 17.0, 6.0, 1.0, 21.0, 2.0, 185.0, 4.0, 0.0]}, {"name": "文山區", "data": [0.0, 0.0, 0.0, 0.0, 0.0, 0.0, 0.0, 0.0, 2.0, 0.0, 3.0, 29.0, 0.0]}, {"name": "非臺北市", "data": [0.0, 0.0, 0.0, 0.0, 0.0, 0.0, 0.0, 0.0, 0.0, 0.0, 0.0, 0.0, 0.0]}]}